gitchurn/__init__.py
gitchurn/__main__.py
gitchurn/gitchurn.py
gitchurn/gitparser.py
gitchurn/ir.py
gitchurn-0.0.4.dist-info/LICENSE
gitchurn-0.0.4.dist-info/METADATA
gitchurn-0.0.4.dist-info/WHEEL
gitchurn-0.0.4.dist-info/entry_points.txt
gitchurn-0.0.4.dist-info/top_level.txt
gitchurn-0.0.4.dist-info/RECORD
