Metadata-Version: 2.1
Name: gitchurn
Version: 0.0.4
Summary: A tool to calculate change churn below the file-level
Home-page: https://github.com/jlefever/gitchurn
Author: Jason Lefever
Author-email: jtl86@drexel.edu
License: UNKNOWN
Project-URL: Source, https://github.com/jlefever/gitchurn
Project-URL: Bug Tracker, https://github.com/jlefever/gitchurn/issues
Platform: UNKNOWN
Classifier: Development Status :: 3 - Alpha
Classifier: Programming Language :: Python :: 3
Classifier: License :: OSI Approved :: Mozilla Public License 2.0 (MPL 2.0)
Classifier: Operating System :: OS Independent
Classifier: Topic :: Software Development :: Version Control :: Git
Classifier: Topic :: Utilities
Requires-Python: >=3.8
License-File: LICENSE
